socialia/__init__.py
socialia/__main__.py
socialia/_branding.py
socialia/analytics.py
socialia/base.py
socialia/linkedin.py
socialia/mcp_server.py
socialia/org.py
socialia/org_files.py
socialia/reddit.py
socialia/scheduler.py
socialia/twitter.py
socialia/youtube.py
socialia/cli/__init__.py
socialia/cli/_commands.py
socialia/cli/_completion_commands.py
socialia/cli/_feed_commands.py
socialia/cli/_mcp_commands.py
socialia/cli/_org_commands.py
socialia/cli/_schedule_commands.py
socialia-0.3.1.dist-info/licenses/LICENSE
socialia-0.3.1.dist-info/METADATA
socialia-0.3.1.dist-info/WHEEL
socialia-0.3.1.dist-info/entry_points.txt
socialia-0.3.1.dist-info/top_level.txt
socialia-0.3.1.dist-info/RECORD
