Metadata-Version: 2.4
Name: socialia
Version: 0.3.1
Summary: Unified social media management - posting, analytics, and insights
Author-email: Yusuke Watanabe <ywatanabe@scitex.ai>
License: AGPL-3.0
Project-URL: Homepage, https://github.com/ywatanabe1989/socialia
Project-URL: Repository, https://github.com/ywatanabe1989/socialia
Keywords: social-media,twitter,cli,automation
Classifier: Development Status :: 3 - Alpha
Classifier: Environment :: Console
Classifier: Intended Audience :: Developers
Classifier: License :: OSI Approved :: GNU Affero General Public License v3
Classifier: Programming Language :: Python :: 3
Classifier: Programming Language :: Python :: 3.10
Classifier: Programming Language :: Python :: 3.11
Classifier: Programming Language :: Python :: 3.12
Requires-Python: >=3.10
License-File: LICENSE
Requires-Dist: requests-oauthlib>=1.3.0
Requires-Dist: requests>=2.28.0
Requires-Dist: argcomplete>=3.0.0
Provides-Extra: reddit
Requires-Dist: praw>=7.7.0; extra == "reddit"
Provides-Extra: mcp
Requires-Dist: mcp>=1.0.0; extra == "mcp"
Provides-Extra: analytics
Requires-Dist: google-analytics-data>=0.18.0; extra == "analytics"
Provides-Extra: youtube
Requires-Dist: google-api-python-client>=2.100.0; extra == "youtube"
Requires-Dist: google-auth-oauthlib>=1.1.0; extra == "youtube"
Provides-Extra: dev
Requires-Dist: pytest; extra == "dev"
Requires-Dist: ruff; extra == "dev"
Provides-Extra: all
Requires-Dist: praw>=7.7.0; extra == "all"
Requires-Dist: mcp>=1.0.0; extra == "all"
Requires-Dist: google-analytics-data>=0.18.0; extra == "all"
Requires-Dist: google-api-python-client>=2.100.0; extra == "all"
Requires-Dist: google-auth-oauthlib>=1.1.0; extra == "all"
Dynamic: license-file
